nonlinear_optimizations/__init__.py
nonlinear_optimizations/function/Function.py
nonlinear_optimizations/function/__init__.py
nonlinear_optimizations-0.1.dist-info/DESCRIPTION.rst
nonlinear_optimizations-0.1.dist-info/METADATA
nonlinear_optimizations-0.1.dist-info/RECORD
nonlinear_optimizations-0.1.dist-info/WHEEL
nonlinear_optimizations-0.1.dist-info/metadata.json
nonlinear_optimizations-0.1.dist-info/top_level.txt
