Metadata-Version: 1.0
Name: nonlinear_optimizations
Version: 0.1
Summary: Nonlinear-optimization algorithms
Home-page: https://github.com/aostrun/Nonlinear-optimizations
Author: Andrijan Ostrun
Author-email: andrijan.ostrun@gmail.com
License: MIT
Platform: UNKNOWN
